dustmaps/__init__.py
dustmaps/bayestar.py
dustmaps/bh.py
dustmaps/chen2014.py
dustmaps/chen2018.py
dustmaps/config.py
dustmaps/csfd.py
dustmaps/decaps.py
dustmaps/dustexceptions.py
dustmaps/edenhofer2023.py
dustmaps/equirectangular_map.py
dustmaps/fetch_utils.py
dustmaps/gaia_tge.py
dustmaps/healpix_map.py
dustmaps/iphas.py
dustmaps/json_serializers.py
dustmaps/leike2020.py
dustmaps/leike_ensslin_2019.py
dustmaps/lenz2017.py
dustmaps/map_base.py
dustmaps/marshall.py
dustmaps/pg2010.py
dustmaps/planck.py
dustmaps/sfd.py
dustmaps/std_paths.py
dustmaps/unstructured_map.py
dustmaps/data/bh/bh.h5
dustmaps/data/bh/rednorth.ascii
dustmaps/data/bh/redsouth.ascii
dustmaps/examples/__init__.py
dustmaps/examples/plot_bayestar.py
dustmaps/examples/plot_bh.py
dustmaps/examples/plot_chen2014.py
dustmaps/examples/plot_comparison.py
dustmaps/examples/plot_iphas.py
dustmaps/examples/plot_lenz2017.py
dustmaps/examples/plot_marshall.py
dustmaps/examples/plot_planck.py
dustmaps/examples/plot_sfd.py
dustmaps/output/.gitignore
dustmaps/tests/__init__.py
dustmaps/tests/argonaut_output_v1.txt
dustmaps/tests/ned_output.json
dustmaps/tests/test_bayestar.py
dustmaps/tests/test_config.json
dustmaps/tests/test_config.py
dustmaps/tests/test_config_with_envvar.json
dustmaps/tests/test_edenhofer2023.py
dustmaps/tests/test_iphas.py
dustmaps/tests/test_marshall.py
dustmaps/tests/test_planck.py
dustmaps/tests/test_serializers.py
dustmaps/tests/test_sfd.py
dustmaps-1.0.14.dist-info/LICENSE.BSD-2-Clause
dustmaps-1.0.14.dist-info/LICENSE.GPL-2.0
dustmaps-1.0.14.dist-info/LICENSE.txt
dustmaps-1.0.14.dist-info/METADATA
dustmaps-1.0.14.dist-info/WHEEL
dustmaps-1.0.14.dist-info/top_level.txt
dustmaps-1.0.14.dist-info/RECORD
