Metadata-Version: 2.1
Name: dustmaps
Version: 1.0.14
Summary: Uniform interface for multiple dust reddening maps.
Home-page: https://github.com/gregreen/dustmaps
Author: Gregory M. Green
Author-email: gregorymgreen@gmail.com
License: GPL-2.0 OR BSD-2-Clause
Download-URL: https://github.com/gregreen/dustmaps/archive/v1.0.14.tar.gz
Platform: UNKNOWN
License-File: LICENSE.BSD-2-Clause
License-File: LICENSE.GPL-2.0
License-File: LICENSE.txt
